hornet/__init__.py
hornet/hornet.py
hornet/nest.py
hornet/tests/__init__.py
hornet/tests/test_hornet.py
hornet-0.1.1.dist-info/DESCRIPTION.rst
hornet-0.1.1.dist-info/METADATA
hornet-0.1.1.dist-info/RECORD
hornet-0.1.1.dist-info/WHEEL
hornet-0.1.1.dist-info/metadata.json
hornet-0.1.1.dist-info/top_level.txt
