Metadata-Version: 2.0
Name: hornet
Version: 0.1.1
Summary: An approach to stacking configurations made up of nested dictionaries
Home-page: https://github.com/bheklilr/hornet
Author: Aaron Stevens
Author-email: bheklilr2@gmail.com
License: MIT
Keywords: config configuration nested stacked json yaml dict dictionary
Platform: UNKNOWN
Classifier: Development Status :: 1 - Planning
Classifier: Intended Audience :: Developers
Classifier: License :: OSI Approved :: MIT License
Classifier: Operating System :: OS Independent
Classifier: Programming Language :: Python :: 3 :: Only
Classifier: Programming Language :: Python :: 3.5
Classifier: Programming Language :: Python :: 3.6
Classifier: Programming Language :: Python :: Implementation :: CPython
